ocelot/__init__.py
ocelot/adaptors/__init__.py
ocelot/adaptors/astra2ocelot.py
ocelot/adaptors/astra_lattice_converter.py
ocelot/adaptors/csrtrack2ocelot.py
ocelot/adaptors/elegant2ocelot.py
ocelot/adaptors/elegant_lattice_converter.py
ocelot/adaptors/genesis.py
ocelot/adaptors/genesis4.py
ocelot/adaptors/longlist2ocelot.py
ocelot/adaptors/mad8.py
ocelot/adaptors/madx.py
ocelot/adaptors/madx_old.py
ocelot/adaptors/openpmd.py
ocelot/adaptors/pmd.py
ocelot/adaptors/srwutil.py
ocelot/adaptors/tfs.py
ocelot/adaptors/wake_t.py
ocelot/common/__init__.py
ocelot/common/conf.py
ocelot/common/globals.py
ocelot/common/math_op.py
ocelot/common/ocelog.py
ocelot/common/py_func.py
ocelot/common/xio.py
ocelot/cpbd/__init__.py
ocelot/cpbd/beam.py
ocelot/cpbd/beam_params.py
ocelot/cpbd/chromaticity.py
ocelot/cpbd/coord_transform.py
ocelot/cpbd/csr.py
ocelot/cpbd/errors.py
ocelot/cpbd/field_map.py
ocelot/cpbd/high_order.py
ocelot/cpbd/io.py
ocelot/cpbd/latticeIO.py
ocelot/cpbd/magnetic_lattice.py
ocelot/cpbd/match.py
ocelot/cpbd/moga.py
ocelot/cpbd/navi.py
ocelot/cpbd/optics.py
ocelot/cpbd/orbit_correction.py
ocelot/cpbd/physics_proc.py
ocelot/cpbd/r_matrix.py
ocelot/cpbd/response_matrix.py
ocelot/cpbd/reswake.py
ocelot/cpbd/sc.py
ocelot/cpbd/tm_utils.py
ocelot/cpbd/touschek.py
ocelot/cpbd/track.py
ocelot/cpbd/wake3D.py
ocelot/cpbd/elements/__init__.py
ocelot/cpbd/elements/aperture.py
ocelot/cpbd/elements/aperture_atom.py
ocelot/cpbd/elements/bend.py
ocelot/cpbd/elements/bend_atom.py
ocelot/cpbd/elements/cavity.py
ocelot/cpbd/elements/cavity_atom.py
ocelot/cpbd/elements/cor_atom.py
ocelot/cpbd/elements/drift.py
ocelot/cpbd/elements/drift_atom.py
ocelot/cpbd/elements/element.py
ocelot/cpbd/elements/hcor.py
ocelot/cpbd/elements/hcor_atom.py
ocelot/cpbd/elements/magnet.py
ocelot/cpbd/elements/marker.py
ocelot/cpbd/elements/marker_atom.py
ocelot/cpbd/elements/matrix.py
ocelot/cpbd/elements/matrix_atom.py
ocelot/cpbd/elements/monitor.py
ocelot/cpbd/elements/monitor_atom.py
ocelot_desy-24.3.1.dist-info/AUTHORS
ocelot_desy-24.3.1.dist-info/LICENSE
ocelot_desy-24.3.1.dist-info/METADATA
ocelot_desy-24.3.1.dist-info/WHEEL
ocelot_desy-24.3.1.dist-info/top_level.txt
ocelot_desy-24.3.1.dist-info/RECORD
